{
  "greeting": "Miss",
  "name": "Sravani",
  "greetingText": "we know u dont have mind thats why we are here.. ",
  "wishText": "eny ur wndfl lfe wth ur____",
  "imagePath": "img/sravani.png",
  "text1": "wake up ...It's your birthday!!! ",
  "textInChatBox": "Happy birthday to you!! Yeee! Many appy returns......",
  "sendButtonLabel": "Send",
  "text2": "That's what we were going to do.",
  "text3": "But then we stopped.",
  "text4": "we realised, we wanted to do something",
  "text4Adjective": "special",
  "text5Entry": "Because,",
  "text5Content": "You are Special",
  "smiley": ":)",
  "bigTextPart1": "S",
  "bigTextPart2": "O",
  "wishHeading": "Happy Birthday!",
  "outroText": "Okay, now come back and tell us if you liked it.",
  "replayText": "Or click, if you want to watch it again.",
  "outroSmiley": ":)"
}
